openweather_api/__init__.py
openweather_api_client-0.0.1.dist-info/LICENSE
openweather_api_client-0.0.1.dist-info/METADATA
openweather_api_client-0.0.1.dist-info/WHEEL
openweather_api_client-0.0.1.dist-info/top_level.txt
openweather_api_client-0.0.1.dist-info/RECORD
